Workbook

Sheet Risk Summary
A1: ENERGY TRADING | RISK INTELLIGENCE
A3: Historical market indicators | B3: Value | C3: Unit | D3: Interpretation
A5: As of | B5: ='Monthly Prices'!A69 -> 46235 | C5: Month | D5: Last observation in frozen EIA dataset
A6: Brent average | B6: ='Monthly Prices'!B69 -> 91.08 | C6: USD/bbl | D6: EIA Europe Brent FOB spot monthly average
A7: WTI average | B7: ='Monthly Prices'!C69 -> 83.9 | C7: USD/bbl | D7: EIA Cushing WTI FOB spot monthly average
A8: Brent minus WTI | B8: ='Monthly Prices'!F69 -> 7.18 | C8: USD/bbl | D8: Benchmark premium, NOT an arbitrage profit
A9: Brent month-on-month | B9: ='Monthly Prices'!D69 -> 0.08739255 | C9: % | D9: Change in monthly averages vs previous month
A10: WTI month-on-month | B10: ='Monthly Prices'!E69 -> 0.042754164 | C10: % | D10: Change in monthly averages vs previous month
A11: Brent annualised 6m vol | B11: ='Monthly Prices'!G69 -> 0.7890767 | C11: % | D11: Six monthly changes sample deviation x sqrt(12)
A12: WTI annualised 6m vol | B12: ='Monthly Prices'!H69 -> 0.68531416 | C12: % | D12: Six monthly changes sample deviation x sqrt(12)
A14: COMMERCIAL SCENARIO | Edit yellow cells on Assumptions
A15: Benchmark | B15: =Assumptions!B5 -> Brent
A16: Current reference price | B16: =IF(B15="Brent",B6,B7) -> 91.08
A17: Position | B17: =Assumptions!B11 -> Buyer
A18: Price shock | B18: =Assumptions!B7 -> 0.15
A19: Fixed-price share | B19: =Assumptions!B8 -> 0.5
A20: Exposure in barrels | B20: =Assumptions!B6 -> 10000
A22: Base signed cash flow ($) | B22: =IF(B17="Buyer",-1,1)*B16*B20 -> -910800
A23: Shocked reference price ($/bbl) | B23: =B16*(1+B18) -> 104.742
A24: Shocked signed cash flow ($) | B24: =IF(B17="Buyer",-1,1)*B23*B20 -> -1047420
A25: Change before coverage proxy ($) | B25: =B24-B22 -> -136620
A26: Change after coverage proxy ($) | B26: =B25*(1-B19) -> -68310
A27: Cash flow after coverage proxy ($) | B27: =B22+B26 -> -979110
A29: Rule-based risk review | B29: =IF(IF(B15="Brent",B11,B12)>=Assumptions!B12,"ELEVATED: review exposure controls","ROUTINE: monitor exposures") -> ELEVATED: review exposure controls
A31: Historical cut | B31: August 2026
A32: Sources | B32: U.S. Energy Information Administration
A33: Important | B33: Illustrative cost/revenue exposure, not actual hedge effectiveness

Sheet Assumptions
A1: ASSUMPTIONS | Blue text on yellow = editable
A3: Parameter | B3: Editable value | C3: Explanation
A5: Benchmark | B5: Brent | C5: Choose Brent or WTI monthly-average benchmark
A6: Exposed volume (barrels) | B6: 10000 | C6: Illustrative future physical purchase or sale volume
A7: Price shock | B7: 0.15 | C7: Hypothetical percentage change in oil benchmark
A8: Fixed-price share | B8: 0.5 | C8: Simple perfect fixed-price coverage proxy, NOT a derivative
A9: Periods per year | B9: 12 | C9: Monthly annualisation convention uses SQRT(12)
A10: Rolling window (months) | B10: 6 | C10: The fixed historical chart uses six MONTHLY changes
A11: Position | B11: Buyer | C11: Buyer incurs cost; seller receives cash flow
A12: Risk-rule threshold | B12: 0.3 | C12: Illustrative annualised-volatility review threshold
A14: READ BEFORE USING
A15: A beginner educational project, not a pricing system or investment recommendation.
A16: Source prices are U.S. EIA MONTHLY averages; they are not live/executable market prices.
A17: Fixed-price share assumes perfect coverage, ignoring basis, premiums, fees and margin.
A18: Changing rolling-window input B10 does NOT change the historical six-month spreadsheet formulas.
A19: 2026 data are Jan–Aug only; do not compare a partial 2026 with full-year totals.

Sheet Monthly Prices
A1: Month | B1: Brent ($/bbl) | C1: WTI ($/bbl) | D1: Brent MoM change | E1: WTI MoM change | F1: Brent - WTI ($/bbl) | G1: Brent 6m ann. vol | H1: WTI 6m ann. vol | I1: Brent EIA source URL | J1: WTI EIA source URL
A2: 44197 | B2: 54.77 | C2: 52 | F2: =B2-C2 -> 2.77 | I2: https://www.eia.gov/dnav/pet/hist/rbrtem.htm | J2: https://www.eia.gov/dnav/pet/hist/rwtcm.htm
A3: 44228 | B3: 62.28 | C3: 59.04 | D3: =B3/B2-1 -> 0.13711886 | E3: =C3/C2-1 -> 0.13538462 | F3: =B3-C3 -> 3.24 | I3: https://www.eia.gov/dnav/pet/hist/rbrtem.htm | J3: https://www.eia.gov/dnav/pet/hist/rwtcm.htm
A4: 44256 | B4: 65.41 | C4: 62.33 | D4: =B4/B3-1 -> 0.050256904 | E4: =C4/C3-1 -> 0.055724932 | F4: =B4-C4 -> 3.08 | I4: https://www.eia.gov/dnav/pet/hist/rbrtem.htm | J4: https://www.eia.gov/dnav/pet/hist/rwtcm.htm
A5: 44287 | B5: 64.81 | C5: 61.72 | D5: =B5/B4-1 -> -0.0091729093 | E5: =C5/C4-1 -> -0.0097866196 | F5: =B5-C5 -> 3.09 | I5: https://www.eia.gov/dnav/pet/hist/rbrtem.htm | J5: https://www.eia.gov/dnav/pet/hist/rwtcm.htm
A6: 44317 | B6: 68.53 | C6: 65.17 | D6: =B6/B5-1 -> 0.05739855 | E6: =C6/C5-1 -> 0.055897602 | F6: =B6-C6 -> 3.36 | I6: https://www.eia.gov/dnav/pet/hist/rbrtem.htm | J6: https://www.eia.gov/dnav/pet/hist/rwtcm.htm
A7: 44348 | B7: 73.16 | C7: 71.38 | D7: =B7/B6-1 -> 0.067561652 | E7: =C7/C6-1 -> 0.095289244 | F7: =B7-C7 -> 1.78 | I7: https://www.eia.gov/dnav/pet/hist/rbrtem.htm | J7: https://www.eia.gov/dnav/pet/hist/rwtcm.htm
A8: 44378 | B8: 75.17 | C8: 72.49 | D8: =B8/B7-1 -> 0.02747403 | E8: =C8/C7-1 -> 0.015550574 | F8: =B8-C8 -> 2.68 | G8: =STDEV(D3:D8)*SQRT(Assumptions!$B$9) -> 0.16832345 | H8: =STDEV(E3:E8)*SQRT(Assumptions!$B$9) -> 0.18189299 | I8: https://www.eia.gov/dnav/pet/hist/rbrtem.htm | J8: https://www.eia.gov/dnav/pet/hist/rwtcm.htm
A9: 44409 | B9: 70.75 | C9: 67.73 | D9: =B9/B8-1 -> -0.058800053 | E9: =C9/C8-1 -> -0.06566423 | F9: =B9-C9 -> 3.02 | G9: =STDEV(D4:D9)*SQRT(Assumptions!$B$9) -> 0.16725913 | H9: =STDEV(E4:E9)*SQRT(Assumptions!$B$9) -> 0.19813435 | I9: https://www.eia.gov/dnav/pet/hist/rbrtem.htm | J9: https://www.eia.gov/dnav/pet/hist/rwtcm.htm
A10: 44440 | B10: 74.49 | C10: 71.65 | D10: =B10/B9-1 -> 0.052862191 | E10: =C10/C9-1 -> 0.057876864 | F10: =B10-C10 -> 2.84 | G10: =STDEV(D5:D10)*SQRT(Assumptions!$B$9) -> 0.16833564 | H10: =STDEV(E5:E10)*SQRT(Assumptions!$B$9) -> 0.19896983 | I10: https://www.eia.gov/dnav/pet/hist/rbrtem.htm | J10: https://www.eia.gov/dnav/pet/hist/rwtcm.htm
A11: 44470 | B11: 83.54 | C11: 81.48 | D11: =B11/B10-1 -> 0.12149282 | E11: =C11/C10-1 -> 0.1371947 | F11: =B11-C11 -> 2.06 | G11: =STDEV(D6:D11)*SQRT(Assumptions!$B$9) -> 0.20585424 | H11: =STDEV(E6:E11)*SQRT(Assumptions!$B$9) -> 0.2415617 | I11: https://www.eia.gov/dnav/pet/hist/rbrtem.htm | J11: https://www.eia.gov/dnav/pet/hist/rwtcm.htm
A12: 44501 | B12: 81.05 | C12: 79.15 | D12: =B12/B11-1 -> -0.029806081 | E12: =C12/C11-1 -> -0.028595974 | F12: =B12-C12 -> 1.9 | G12: =STDEV(D7:D12)*SQRT(Assumptions!$B$9) -> 0.2285939 | H12: =STDEV(E7:E12)*SQRT(Assumptions!$B$9) -> 0.26453337 | I12: https://www.eia.gov/dnav/pet/hist/rbrtem.htm | J12: https://www.eia.gov/dnav/pet/hist/rwtcm.htm
A13: 44531 | B13: 74.17 | C13: 71.71 | D13: =B13/B12-1 -> -0.084885873 | E13: =C13/C12-1 -> -0.093998737 | F13: =B13-C13 -> 2.46 | G13: =STDEV(D8:D13)*SQRT(Assumptions!$B$9) -> 0.26710612 | H13: =STDEV(E8:E13)*SQRT(Assumptions!$B$9) -> 0.29514417 | I13: https://www.eia.gov/dnav/pet/hist/rbrtem.htm | J13: https://www.eia.gov/dnav/pet/hist/rwtcm.htm
A14: 44562 | B14: 86.51 | C14: 83.22 | D14: =B14/B13-1 -> 0.16637454 | E14: =C14/C13-1 -> 0.1605076 | F14: =B14-C14 -> 3.29 | G14: =STDEV(D9:D14)*SQRT(Assumptions!$B$9) -> 0.35369636 | H14: =STDEV(E9:E14)*SQRT(Assumptions!$B$9) -> 0.37062352 | I14: https://www.eia.gov/dnav/pet/hist/rbrtem.htm | J14: https://www.eia.gov/dnav/pet/hist/rwtcm.htm
A15: 44593 | B15: 97.13 | C15: 91.64 | D15: =B15/B14-1 -> 0.12276037 | E15: =C15/C14-1 -> 0.1011776 | F15: =B15-C15 -> 5.49 | G15: =STDEV(D10:D15)*SQRT(Assumptions!$B$9) -> 0.33984534 | H15: =STDEV(E10:E15)*SQRT(Assumptions!$B$9) -> 0.34367831 | I15: https://www.eia.gov/dnav/pet/hist/rbrtem.htm | J15: https://www.eia.gov/dnav/pet/hist/rwtcm.htm
A16: 44621 | B16: 117.25 | C16: 108.5 | D16: =B16/B15-1 -> 0.20714506 | E16: =C16/C15-1 -> 0.18398079 | F16: =B16-C16 -> 8.75 | G16: =STDEV(D11:D16)*SQRT(Assumptions!$B$9) -> 0.39899616 | H16: =STDEV(E11:E16)*SQRT(Assumptions!$B$9) -> 0.38889673 | I16: https://www.eia.gov/dnav/pet/hist/rbrtem.htm | J16: https://www.eia.gov/dnav/pet/hist/rwtcm.htm
A17: 44652 | B17: 104.58 | C17: 101.78 | D17: =B17/B16-1 -> -0.1080597 | E17: =C17/C16-1 -> -0.061935484 | F17: =B17-C17 -> 2.8 | G17: =STDEV(D12:D17)*SQRT(Assumptions!$B$9) -> 0.47234131 | H17: =STDEV(E12:E17)*SQRT(Assumptions!$B$9) -> 0.4156134 | I17: https://www.eia.gov/dnav/pet/hist/rbrtem.htm | J17: https://www.eia.gov/dnav/pet/hist/rwtcm.htm
A18: 44682 | B18: 113.34 | C18: 109.55 | D18: =B18/B17-1 -> 0.083763626 | E18: =C18/C17-1 -> 0.076341128 | F18: =B18-C18 -> 3.79 | G18: =STDEV(D13:D18)*SQRT(Assumptions!$B$9) -> 0.45585362 | H18: =STDEV(E13:E18)*SQRT(Assumptions!$B$9) -> 0.39803528 | I18: https://www.eia.gov/dnav/pet/hist/rbrtem.htm | J18: https://www.eia.gov/dnav/pet/hist/rwtcm.htm
A19: 44713 | B19: 122.71 | C19: 114.84 | D19: =B19/B18-1 -> 0.082671608 | E19: =C19/C18-1 -> 0.048288453 | F19: =B19-C19 -> 7.87 | G19: =STDEV(D14:D19)*SQRT(Assumptions!$B$9) -> 0.37920039 | H19: =STDEV(E14:E19)*SQRT(Assumptions!$B$9) -> 0.30504798 | I19: https://www.eia.gov/dnav/pet/hist/rbrtem.htm | J19: https://www.eia.gov/dnav/pet/hist/rwtcm.htm
... A69: 46235 | B69: 91.08 | C69: 83.9 | D69: =B69/B68-1 -> 0.08739255 | E69: =C69/C68-1 -> 0.042754164 | F69: =B69-C69 -> 7.18 | G69: =STDEV(D64:D69)*SQRT(Assumptions!$B$9) -> 0.7890767 | H69: =STDEV(E64:E69)*SQRT(Assumptions!$B$9) -> 0.68531416 | I69: https://www.eia.gov/dnav/pet/hist/rbrtem.htm | J69: https://www.eia.gov/dnav/pet/hist/rwtcm.htm

Sheet Scenario Grid
A1: SCENARIO GRID | Buyer / Seller price-shock sensitivity
A3: Price shock | B3: Shocked ($/bbl) | C3: Impact before proxy ($) | D3: Impact after proxy ($) | E3: Interpretation
A4: -0.2 | B4: ='Risk Summary'!$B$16*(1+A4) -> 72.864 | C4: =IF('Risk Summary'!$B$17="Buyer",-1,1)*'Risk Summary'!$B$20*'Risk Summary'!$B$16*A4 -> 182160 | D4: =C4*(1-'Risk Summary'!$B$19) -> 91080 | E4: =IF(D4>0,"Favourable",IF(D4<0,"Unfavourable","No change")) -> Favourable
A5: -0.1 | B5: ='Risk Summary'!$B$16*(1+A5) -> 81.972 | C5: =IF('Risk Summary'!$B$17="Buyer",-1,1)*'Risk Summary'!$B$20*'Risk Summary'!$B$16*A5 -> 91080 | D5: =C5*(1-'Risk Summary'!$B$19) -> 45540 | E5: =IF(D5>0,"Favourable",IF(D5<0,"Unfavourable","No change")) -> Favourable
A6: -0.05 | B6: ='Risk Summary'!$B$16*(1+A6) -> 86.526 | C6: =IF('Risk Summary'!$B$17="Buyer",-1,1)*'Risk Summary'!$B$20*'Risk Summary'!$B$16*A6 -> 45540 | D6: =C6*(1-'Risk Summary'!$B$19) -> 22770 | E6: =IF(D6>0,"Favourable",IF(D6<0,"Unfavourable","No change")) -> Favourable
A7: 0 | B7: ='Risk Summary'!$B$16*(1+A7) -> 91.08 | C7: =IF('Risk Summary'!$B$17="Buyer",-1,1)*'Risk Summary'!$B$20*'Risk Summary'!$B$16*A7 -> 0 | D7: =C7*(1-'Risk Summary'!$B$19) -> 0 | E7: =IF(D7>0,"Favourable",IF(D7<0,"Unfavourable","No change")) -> No change
A8: 0.05 | B8: ='Risk Summary'!$B$16*(1+A8) -> 95.634 | C8: =IF('Risk Summary'!$B$17="Buyer",-1,1)*'Risk Summary'!$B$20*'Risk Summary'!$B$16*A8 -> -45540 | D8: =C8*(1-'Risk Summary'!$B$19) -> -22770 | E8: =IF(D8>0,"Favourable",IF(D8<0,"Unfavourable","No change")) -> Unfavourable
A9: 0.1 | B9: ='Risk Summary'!$B$16*(1+A9) -> 100.188 | C9: =IF('Risk Summary'!$B$17="Buyer",-1,1)*'Risk Summary'!$B$20*'Risk Summary'!$B$16*A9 -> -91080 | D9: =C9*(1-'Risk Summary'!$B$19) -> -45540 | E9: =IF(D9>0,"Favourable",IF(D9<0,"Unfavourable","No change")) -> Unfavourable
A10: 0.2 | B10: ='Risk Summary'!$B$16*(1+A10) -> 109.296 | C10: =IF('Risk Summary'!$B$17="Buyer",-1,1)*'Risk Summary'!$B$20*'Risk Summary'!$B$16*A10 -> -182160 | D10: =C10*(1-'Risk Summary'!$B$19) -> -91080 | E10: =IF(D10>0,"Favourable",IF(D10<0,"Unfavourable","No change")) -> Unfavourable
A13: Interpretation | B13: Positive impact = favourable signed cash-flow change; negative = unfavourable.
A14: Note | B14: Fixed-price share is a simplistic proxy, not a valuation of a futures or options hedge.

Sheet Sources & Notes
A1: METHODOLOGY | Sources & caveats
A3: Dataset | B3: Official EIA source | C3: Description
A4: Brent monthly spot average | B4: https://www.eia.gov/dnav/pet/hist/rbrtem.htm | C4: Europe Brent Spot Price FOB, USD/bbl
A5: WTI monthly spot average | B5: https://www.eia.gov/dnav/pet/hist/rwtcm.htm | C5: Cushing, Oklahoma WTI Spot Price FOB, USD/bbl
A7: DEFINITIONS / IMPORTANT LIMITS
A9: Historical snapshot | B9: January 2021 – August 2026; 68 complete months per benchmark
A10: Source accessed | B10: 20 October 2026; frozen offline educational snapshot
A11: Monthly price | B11: EIA average price across a month; not a first-day close or quoted futures price
A12: Monthly change | B12: Current monthly average / previous monthly average - 1
A13: Spread | B13: Brent monthly average minus WTI monthly average
A14: Rolling volatility | B14: Sample standard deviation of six monthly changes times sqrt(12)
A15: Coverage proxy | B15: Pre-fixed share is insensitive to price shock, by assumption
A16: Buyer impact | B16: Signed change in cash flow is negative when reference price rises
A17: Seller impact | B17: Signed change in cash flow is positive when reference price rises
A18: Excluded | B18: Futures curves, funding, transport, FX, basis, margin, credit, storage, taxes
A19: Incomplete year | B19: 2026 includes Jan to Aug, not 12 months
A20: Decision status | B20: These are educational conditional prompts, NOT trading signals
